setup.py
time_series_analysis/__init__.py
time_series_analysis/console.py
time_series_analysis/tools.py
time_series_analysis.egg-info/PKG-INFO
time_series_analysis.egg-info/SOURCES.txt
time_series_analysis.egg-info/dependency_links.txt
time_series_analysis.egg-info/entry_points.txt
time_series_analysis.egg-info/not-zip-safe
time_series_analysis.egg-info/requires.txt
time_series_analysis.egg-info/top_level.txt