Metadata-Version: 1.0
Name: time-series-analysis
Version: 0.1.2
Summary: Contains tools for analyzing time-series data on the command-line.
Home-page: https://github.com/skuenzli/time-series-analysis
Author: Stephen Kuenzli
Author-email: UNKNOWN
License: Apache 2.0
Platform: UNKNOWN
